gptsum/__init__.py
gptsum/__main__.py
gptsum/checksum.py
gptsum/cli.py
gptsum/gpt.py
gptsum/py.typed
gptsum-0.5.0.dist-info/LICENSE
gptsum-0.5.0.dist-info/METADATA
gptsum-0.5.0.dist-info/WHEEL
gptsum-0.5.0.dist-info/entry_points.txt
gptsum-0.5.0.dist-info/RECORD
