Metadata-Version: 2.1
Name: gptsum
Version: 0.5.0
Summary: A tool to make disk images using GPT partitions self-verifiable
Home-page: https://github.com/NicolasT/gptsum
License: Apache-2.0
Keywords: gpt,diskimage,checksum
Author: Nicolas Trangez
Author-email: ikke@nicolast.be
Requires-Python: >=3.8.17,<4.0.0
Classifier: Development Status :: 4 - Beta
Classifier: Environment :: Console
Classifier: Intended Audience :: Developers
Classifier: Intended Audience :: Information Technology
Classifier: Intended Audience :: System Administrators
Classifier: License :: OSI Approved :: Apache Software License
Classifier: Operating System :: MacOS
Classifier: Operating System :: MacOS :: MacOS X
Classifier: Operating System :: Microsoft
Classifier: Operating System :: Microsoft :: Windows
Classifier: Operating System :: POSIX
Classifier: Operating System :: POSIX :: Linux
Classifier: Programming Language :: Python :: 3
Classifier: Programming Language :: Python :: 3.9
Classifier: Programming Language :: Python :: 3.10
Classifier: Programming Language :: Python :: 3.11
Classifier: Programming Language :: Python :: 3.12
Classifier: Programming Language :: Python :: 3.13
Classifier: Programming Language :: Python :: 3 :: Only
Classifier: Programming Language :: Python :: 3.8
Classifier: Topic :: System
Classifier: Topic :: System :: Software Distribution
Classifier: Typing :: Typed
Project-URL: Changelog, https://github.com/NicolasT/gptsum/releases
Project-URL: Documentation, https://nicolast.github.io/gptsum/
Project-URL: Issues, https://github.com/NicolasT/gptsum/issues
Project-URL: Pull Requests, https://github.com/NicolasT/gptsum/pulls
Project-URL: Repository, https://github.com/NicolasT/gptsum.git
